_version.py
pypolyline/__init__.py
pypolyline/cutil.cpython-314-aarch64-linux-gnu.so
pypolyline/cutil.pyx
pypolyline/header.h
pypolyline/libpolylineffi.so
pypolyline/pypolyline_p.pxd
pypolyline/stdbool.h
pypolyline-0.5.6.dist-info/METADATA
pypolyline-0.5.6.dist-info/WHEEL
pypolyline-0.5.6.dist-info/top_level.txt
pypolyline-0.5.6.dist-info/RECORD
pypolyline-0.5.6.dist-info/licenses/LICENSE.md
